TakeAicHelper/__init__.py
TakeAicHelper/__main__.py
TakeAicHelper/metrics.py
TakeAicHelper-0.0.5.dist-info/METADATA
TakeAicHelper-0.0.5.dist-info/WHEEL
TakeAicHelper-0.0.5.dist-info/top_level.txt
TakeAicHelper-0.0.5.dist-info/RECORD
