Metadata-Version: 2.1
Name: TakeAicHelper
Version: 0.0.5
Summary: Métricas para analisar a conversa entre pessoas e chatbots
Home-page: UNKNOWN
Author: Caio Souza
Author-email: caios@take.net
License: UNKNOWN
Platform: UNKNOWN
Classifier: Development Status :: 4 - Beta
Classifier: License :: OSI Approved :: MIT License
Classifier: Operating System :: OS Independent
Classifier: Programming Language :: Python :: 3
Requires-Dist: pandas
Requires-Dist: plotly
